{
  "generated_from": "data/snapshots/external_review/2026-02-09-independent",
  "inputs": {
    "reward_added_events_file": "grm_rewardAdded_events.csv",
    "canonical_revenue_file": "staker_revenue_canonical_summary.json",
    "attribution_summary_file": "payout_attribution_summary.json",
    "lvusdc_nav_snapshot_file": "base_rpc_lvusdc_convertToAssets_latest.json"
  },
  "emissions_component": {
    "event_count": 4,
    "reward_token": "SUMR",
    "total_raw": "3396151000000000000000000",
    "decimals": 18,
    "total_sumr_tokens": 3396151.0,
    "block_min": 25649474,
    "block_max": 36517084
  },
  "revenue_component_token_native": {
    "USDC": {
      "deposited": 5833.985241,
      "claimed_attributed": 5833.985241,
      "unclaimed_residual": 0.0
    },
    "LVUSDC": {
      "deposited": 8301.739885,
      "claimed_attributed": 1938.217454,
      "unclaimed_residual": 6363.522431
    }
  },
  "lvusdc_nav_convertToAssets": {
    "snapshot_available": true,
    "source_file": "base_rpc_lvusdc_convertToAssets_latest.json",
    "method": "convertToAssets(1 LVUSDC) via historical eth_call",
    "shares_input_raw": "1000000",
    "asset_address": "0x833589fcd6edb6e08f4c7c32d4f71b54bda02913",
    "lvusdc_decimals": 6,
    "asset_decimals": 6,
    "funding_execute_block": 41932733,
    "observation_block": 42706804,
    "snapshot_count": 89,
    "block_min": 41932733,
    "block_max": 42706804,
    "summary": {
      "block_min": 41932733,
      "block_max": 42706804,
      "funding_block_assets_per_lvusdc": "1.058317",
      "observation_block_assets_per_lvusdc": "1.059817",
      "assets_per_lvusdc_min": "1.058317",
      "assets_per_lvusdc_max": "1.059817"
    }
  },
  "lvusdc_usdc_equivalent_valuation": {
    "method_version": "lvusdc_convertToAssets_block_level_v1",
    "segment_methods": {
      "deposited": "sum(cycle deposited LVUSDC * convertToAssets at governor_execute_block)",
      "claimed_attributed": "sum(attributed claim LVUSDC * convertToAssets at each claim event block)",
      "unclaimed_residual": "sum(cycle unclaimed LVUSDC residual * convertToAssets at observation block)"
    },
    "segments": {
      "deposited": {
        "lvusdc_tokens_total": 8301.739885,
        "usdc_equivalent_total": 8785.872449873545,
        "nav_source_blocks": [
          41932733
        ],
        "details": [
          {
            "label": "SIP3.13.1",
            "lvusdc_tokens": 8301.739885,
            "valuation_block": 41932733,
            "nav_source_block": 41932733,
            "nav_lookup_mode": "exact",
            "usdc_per_lvusdc": 1.058317,
            "usdc_equivalent": 8785.872449873545
          }
        ]
      },
      "claimed_attributed": {
        "lvusdc_tokens_total": 1938.217454,
        "usdc_equivalent_total": 2052.153624492847,
        "nav_source_blocks": [
          41947817,
          41949222,
          41949608,
          41949842,
          41953994,
          41960141,
          41974230,
          41977510,
          41985130,
          41988696,
          42000774,
          42003925,
          42009515,
          42011613,
          42021519,
          42027100,
          42028459,
          42029941,
          42033894,
          42059201,
          42059879,
          42060008,
          42068608,
          42084357,
          42090109,
          42092815,
          42099675,
          42102747,
          42117811,
          42119093,
          42119133,
          42129922,
          42131271,
          42131338,
          42133673,
          42142957,
          42157076,
          42157309,
          42157445,
          42180200,
          42183421,
          42183463,
          42183513,
          42183564,
          42184610,
          42189354,
          42198355,
          42218219,
          42226581,
          42226620,
          42227483,
          42227751,
          42236361,
          42271873,
          42275402,
          42281425,
          42301705,
          42309944,
          42325670,
          42339008,
          42346487,
          42355037,
          42358210,
          42395067,
          42433033,
          42454301,
          42458288,
          42476690,
          42478417,
          42494522,
          42518735,
          42522033,
          42552745,
          42552917,
          42553000,
          42580607,
          42585628,
          42590279,
          42597151,
          42608678,
          42623069,
          42632305,
          42637037,
          42656355
        ],
        "details": [
          {
            "label": "SIP3.13.1",
            "valuation_method": "claim-event block convertToAssets with sequential attribution cap allocation",
            "attributed_claim_tokens_target": 1938.217454,
            "attributed_claim_tokens_valued": 1938.217454,
            "attributed_claim_tokens_unvalued": 0.0,
            "claim_events_file": "payout_attribution_sip3_13_1_claim_events.csv",
            "claim_events_count": 87,
            "nav_source_blocks": [
              41947817,
              41949222,
              41949608,
              41949842,
              41953994,
              41960141,
              41974230,
              41977510,
              41985130,
              41988696,
              42000774,
              42003925,
              42009515,
              42011613,
              42021519,
              42027100,
              42028459,
              42029941,
              42033894,
              42059201,
              42059879,
              42060008,
              42068608,
              42084357,
              42090109,
              42092815,
              42099675,
              42102747,
              42117811,
              42119093,
              42119133,
              42129922,
              42131271,
              42131338,
              42133673,
              42142957,
              42157076,
              42157309,
              42157445,
              42180200,
              42183421,
              42183463,
              42183513,
              42183564,
              42184610,
              42189354,
              42198355,
              42218219,
              42226581,
              42226620,
              42227483,
              42227751,
              42236361,
              42271873,
              42275402,
              42281425,
              42301705,
              42309944,
              42325670,
              42339008,
              42346487,
              42355037,
              42358210,
              42395067,
              42433033,
              42454301,
              42458288,
              42476690,
              42478417,
              42494522,
              42518735,
              42522033,
              42552745,
              42552917,
              42553000,
              42580607,
              42585628,
              42590279,
              42597151,
              42608678,
              42623069,
              42632305,
              42637037,
              42656355
            ],
            "nav_lookup_modes": [
              "exact"
            ],
            "missing_nav_blocks": [],
            "usdc_equivalent": 2052.153624492847
          }
        ]
      },
      "unclaimed_residual": {
        "lvusdc_tokens_total": 6363.522431,
        "usdc_equivalent_total": 6744.169252255127,
        "nav_source_blocks": [
          42706804
        ],
        "details": [
          {
            "label": "SIP3.13.1",
            "lvusdc_tokens": 6363.522431,
            "valuation_block": 42706804,
            "nav_source_block": 42706804,
            "nav_lookup_mode": "exact",
            "usdc_per_lvusdc": 1.059817,
            "usdc_equivalent": 6744.169252255127
          }
        ]
      }
    }
  },
  "revenue_component_usdc_equivalent": {
    "deposited": 14619.857690873545,
    "claimed_attributed": 7886.138865492847,
    "unclaimed_residual": 6744.169252255127
  },
  "window_comparability": {
    "campaign_analysis_start_block": 40757499,
    "campaign_analysis_end_block": 41932732,
    "emissions_events_in_campaign_window": 0,
    "note": "Emissions-vs-revenue comparability depends on overlapping windows. Current emissions events may sit outside payout campaign windows."
  },
  "usd_decomposition_formula": {
    "emissions_usd_formula": "emissions_sumr_tokens * sumr_price_usd",
    "revenue_usd_equivalent_basis": "USDC direct + LVUSDC valued by convertToAssets at segment-specific historical blocks",
    "break_even_sumr_price_for_emissions_equal_revenue_deposited": 0.004304831466820393
  },
  "limitations": [
    "SUMR USD valuation is formula-based unless an external price snapshot is pinned.",
    "LVUSDC valuation is bounded by available NAV snapshots and attribution model assumptions."
  ]
}